onegov.page-0.2.1-py3.4-nspkg.pth
onegov/page/__init__.py
onegov/page/collection.py
onegov/page/model.py
onegov/page/upgrade.py
onegov/page/.gitignore
onegov/page/tests/test_collection.py
onegov/page/tests/test_polymorphic.py
onegov.page-0.2.1.dist-info/top_level.txt
onegov.page-0.2.1.dist-info/entry_points.txt
onegov.page-0.2.1.dist-info/namespace_packages.txt
onegov.page-0.2.1.dist-info/METADATA
onegov.page-0.2.1.dist-info/DESCRIPTION.rst
onegov.page-0.2.1.dist-info/metadata.json
onegov.page-0.2.1.dist-info/WHEEL
onegov.page-0.2.1.dist-info/RECORD
